{
"meta":{"test_sets":[],"test_metrics":[],"learn_metrics":[{"best_value":"Min","name":"RMSE"}],"launch_mode":"Train","parameters":"","iteration_count":100,"learn_sets":["learn"],"name":"experiment"},
"iterations":[
{"learn":[11624.23031],"iteration":0,"passed_time":0.0009545302622,"remaining_time":0.09449849595},
{"learn":[11190.93135],"iteration":1,"passed_time":0.001403609118,"remaining_time":0.06877684676},
{"learn":[10798.51909],"iteration":2,"passed_time":0.002160639258,"remaining_time":0.06986066934},
{"learn":[10400.32453],"iteration":3,"passed_time":0.002927891514,"remaining_time":0.07026939633},
{"learn":[10063.33131],"iteration":4,"passed_time":0.003699188347,"remaining_time":0.07028457859},
{"learn":[9725.333405],"iteration":5,"passed_time":0.004454467849,"remaining_time":0.06978666297},
{"learn":[9392.248913],"iteration":6,"passed_time":0.005185811907,"remaining_time":0.06889721533},
{"learn":[9088.09617],"iteration":7,"passed_time":0.005928907372,"remaining_time":0.06818243478},
{"learn":[8820.044734],"iteration":8,"passed_time":0.006750231009,"remaining_time":0.06825233575},
{"learn":[8558.114653],"iteration":9,"passed_time":0.007181743119,"remaining_time":0.06463568807},
{"learn":[8288.905548],"iteration":10,"passed_time":0.007953754292,"remaining_time":0.06435310291},
{"learn":[8059.172585],"iteration":11,"passed_time":0.008717726617,"remaining_time":0.06392999519},
{"learn":[7839.668855],"iteration":12,"passed_time":0.009478247972,"remaining_time":0.06343135182},
{"learn":[7655.652209],"iteration":13,"passed_time":0.01023811535,"remaining_time":0.06289128003},
{"learn":[7459.684219],"iteration":14,"passed_time":0.01078081309,"remaining_time":0.06109127418},
{"learn":[7263.642143],"iteration":15,"passed_time":0.01153936246,"remaining_time":0.06058165293},
{"learn":[7083.769219],"iteration":16,"passed_time":0.01231534778,"remaining_time":0.06012787448},
{"learn":[6915.204132],"iteration":17,"passed_time":0.01306542568,"remaining_time":0.05952027254},
{"learn":[6748.276415],"iteration":18,"passed_time":0.01383138005,"remaining_time":0.05896535705},
{"learn":[6583.399036],"iteration":19,"passed_time":0.01456910287,"remaining_time":0.05827641147},
{"learn":[6429.468714],"iteration":20,"passed_time":0.01511384301,"remaining_time":0.05685683801},
{"learn":[6302.929674],"iteration":21,"passed_time":0.0156684632,"remaining_time":0.05555182407},
{"learn":[6187.847182],"iteration":22,"passed_time":0.01642370246,"remaining_time":0.05498369953},
{"learn":[6066.424291],"iteration":23,"passed_time":0.01717094311,"remaining_time":0.05437465318},
{"learn":[5943.882857],"iteration":24,"passed_time":0.01794106279,"remaining_time":0.05382318837},
{"learn":[5837.456063],"iteration":25,"passed_time":0.01870910988,"remaining_time":0.05324900503},
{"learn":[5735.494742],"iteration":26,"passed_time":0.01947736824,"remaining_time":0.05266103266},
{"learn":[5649.004432],"iteration":27,"passed_time":0.02023593774,"remaining_time":0.05203526847},
{"learn":[5564.385096],"iteration":28,"passed_time":0.02105824705,"remaining_time":0.05155639796},
{"learn":[5484.055776],"iteration":29,"passed_time":0.02182676701,"remaining_time":0.05092912303},
{"learn":[5406.134586],"iteration":30,"passed_time":0.02260578074,"remaining_time":0.05031609261},
{"learn":[5334.692742],"iteration":31,"passed_time":0.02336947135,"remaining_time":0.04966012662},
{"learn":[5263.611832],"iteration":32,"passed_time":0.02412586764,"remaining_time":0.04898282218},
{"learn":[5195.069498],"iteration":33,"passed_time":0.02488723413,"remaining_time":0.04831051331},
{"learn":[5133.04719],"iteration":34,"passed_time":0.02531427909,"remaining_time":0.0470122326},
{"learn":[5079.0022],"iteration":35,"passed_time":0.0260696089,"remaining_time":0.04634597138},
{"learn":[5021.440205],"iteration":36,"passed_time":0.02683457728,"remaining_time":0.04569130726},
{"learn":[4970.152377],"iteration":37,"passed_time":0.02758426279,"remaining_time":0.04500590245},
{"learn":[4926.487464],"iteration":38,"passed_time":0.02834224874,"remaining_time":0.04433018393},
{"learn":[4878.018489],"iteration":39,"passed_time":0.02909625048,"remaining_time":0.04364437572},
{"learn":[4830.045944],"iteration":40,"passed_time":0.0298548904,"remaining_time":0.04296191545},
{"learn":[4787.118133],"iteration":41,"passed_time":0.03062650919,"remaining_time":0.04229375079},
{"learn":[4749.564331],"iteration":42,"passed_time":0.03139677979,"remaining_time":0.04161898716},
{"learn":[4717.002755],"iteration":43,"passed_time":0.03214261188,"remaining_time":0.04090877876},
{"learn":[4689.5555],"iteration":44,"passed_time":0.03292197775,"remaining_time":0.0402379728},
{"learn":[4657.447694],"iteration":45,"passed_time":0.03368809309,"remaining_time":0.03954689189},
{"learn":[4637.550493],"iteration":46,"passed_time":0.03401920512,"remaining_time":0.03836208236},
{"learn":[4609.830348],"iteration":47,"passed_time":0.03478587383,"remaining_time":0.03768469664},
{"learn":[4588.785599],"iteration":48,"passed_time":0.0351188874,"remaining_time":0.03655231138},
{"learn":[4562.821023],"iteration":49,"passed_time":0.0359112095,"remaining_time":0.0359112095},
{"learn":[4546.800507],"iteration":50,"passed_time":0.0362629871,"remaining_time":0.03484090917},
{"learn":[4530.005107],"iteration":51,"passed_time":0.03700616305,"remaining_time":0.03415953512},
{"learn":[4507.745929],"iteration":52,"passed_time":0.03775574795,"remaining_time":0.03348151233},
{"learn":[4488.295306],"iteration":53,"passed_time":0.03853054606,"remaining_time":0.03282231701},
{"learn":[4473.97545],"iteration":54,"passed_time":0.03930798018,"remaining_time":0.0321610747},
{"learn":[4456.136101],"iteration":55,"passed_time":0.04019934663,"remaining_time":0.03158520092},
{"learn":[4441.478817],"iteration":56,"passed_time":0.04094368967,"remaining_time":0.03088734484},
{"learn":[4426.476855],"iteration":57,"passed_time":0.04172375982,"remaining_time":0.03021375711},
{"learn":[4413.179731],"iteration":58,"passed_time":0.04249299412,"remaining_time":0.02952902981},
{"learn":[4399.326591],"iteration":59,"passed_time":0.04323656246,"remaining_time":0.02882437497},
{"learn":[4384.681029],"iteration":60,"passed_time":0.04399872378,"remaining_time":0.0281303316},
{"learn":[4373.840354],"iteration":61,"passed_time":0.04475782651,"remaining_time":0.02743221625},
{"learn":[4362.315353],"iteration":62,"passed_time":0.04551372981,"remaining_time":0.02673028576},
{"learn":[4350.901764],"iteration":63,"passed_time":0.04626537724,"remaining_time":0.0260242747},
{"learn":[4336.50818],"iteration":64,"passed_time":0.04701544507,"remaining_time":0.02531600888},
{"learn":[4325.541363],"iteration":65,"passed_time":0.04777366243,"remaining_time":0.02461067458},
{"learn":[4315.39485],"iteration":66,"passed_time":0.04852401197,"remaining_time":0.02389988649},
{"learn":[4312.517038],"iteration":67,"passed_time":0.04878438414,"remaining_time":0.02295735724},
{"learn":[4302.484633],"iteration":68,"passed_time":0.04954073012,"remaining_time":0.02225742948},
{"learn":[4296.133938],"iteration":69,"passed_time":0.05028670307,"remaining_time":0.02155144417},
{"learn":[4286.400845],"iteration":70,"passed_time":0.05108489584,"remaining_time":0.02086566168},
{"learn":[4278.100981],"iteration":71,"passed_time":0.05185676616,"remaining_time":0.02016652017},
{"learn":[4272.902926],"iteration":72,"passed_time":0.05241192964,"remaining_time":0.01938523425},
{"learn":[4267.849637],"iteration":73,"passed_time":0.05316641432,"remaining_time":0.01868009152},
{"learn":[4257.726681],"iteration":74,"passed_time":0.05391766936,"remaining_time":0.01797255645},
{"learn":[4256.294627],"iteration":75,"passed_time":0.05417157222,"remaining_time":0.01710681228},
{"learn":[4250.823928],"iteration":76,"passed_time":0.05472442164,"remaining_time":0.01634625582},
{"learn":[4245.284666],"iteration":77,"passed_time":0.05548164295,"remaining_time":0.01564866852},
{"learn":[4236.458591],"iteration":78,"passed_time":0.05624330121,"remaining_time":0.01495075095},
{"learn":[4229.007393],"iteration":79,"passed_time":0.05700671011,"remaining_time":0.01425167753},
{"learn":[4224.442508],"iteration":80,"passed_time":0.05778994951,"remaining_time":0.01355566717},
{"learn":[4219.412414],"iteration":81,"passed_time":0.0585572722,"remaining_time":0.01285403536},
{"learn":[4216.670579],"iteration":82,"passed_time":0.05910742524,"remaining_time":0.01210634011},
{"learn":[4210.621738],"iteration":83,"passed_time":0.05987184025,"remaining_time":0.01140416005},
{"learn":[4207.032231],"iteration":84,"passed_time":0.06062505722,"remaining_time":0.01069853951},
{"learn":[4201.077338],"iteration":85,"passed_time":0.06137790193,"remaining_time":0.009991751477},
{"learn":[4199.369961],"iteration":86,"passed_time":0.06181301593,"remaining_time":0.009236427667},
{"learn":[4190.304251],"iteration":87,"passed_time":0.06259301564,"remaining_time":0.008535411224},
{"learn":[4182.625732],"iteration":88,"passed_time":0.0633446832,"remaining_time":0.007829118148},
{"learn":[4177.022562],"iteration":89,"passed_time":0.06411884745,"remaining_time":0.007124316384},
{"learn":[4171.901216],"iteration":90,"passed_time":0.06487191351,"remaining_time":0.006415903534},
{"learn":[4165.881398],"iteration":91,"passed_time":0.06570569755,"remaining_time":0.005713538917},
{"learn":[4158.128582],"iteration":92,"passed_time":0.06649681199,"remaining_time":0.005005136386},
{"learn":[4152.821905],"iteration":93,"passed_time":0.06728160081,"remaining_time":0.004294570264},
{"learn":[4147.526104],"iteration":94,"passed_time":0.06803989865,"remaining_time":0.003581047297},
{"learn":[4143.461153],"iteration":95,"passed_time":0.06878533836,"remaining_time":0.002866055765},
{"learn":[4137.540968],"iteration":96,"passed_time":0.0695288564,"remaining_time":0.002150377002},
{"learn":[4129.605928],"iteration":97,"passed_time":0.07028599721,"remaining_time":0.001434408106},
{"learn":[4128.056111],"iteration":98,"passed_time":0.07074013682,"remaining_time":0.0007145468365},
{"learn":[4121.597762],"iteration":99,"passed_time":0.07150254966,"remaining_time":0}
]}